dial_clean
