Metadata-Version: 1.0
Name: dial-clean
Version: 0.1.1
Summary: My first Python library
Home-page: https://github.com/everks/dial-clean
Author: songyi
Author-email: 757503218@qq.com
License: UNKNOWN
Platform: UNKNOWN
